auto_paste_from_script/__init__.py
auto_paste_from_script-1.0.dist-info/METADATA
auto_paste_from_script-1.0.dist-info/WHEEL
auto_paste_from_script-1.0.dist-info/top_level.txt
auto_paste_from_script-1.0.dist-info/RECORD
