Metadata-Version: 2.1
Name: auto-paste-from-script
Version: 1.0
Summary: Package to execute lines from scripts into Python interpreters
Home-page: https://github.com/salayatana66/auto-paste-from-script
Author: Andrea Schioppa
Author-email: andrej.schioppa@gmail.com
License: UNKNOWN
Platform: UNKNOWN
Classifier: Programming Language :: Python :: 3
Classifier: License :: OSI Approved :: MIT License
Classifier: Operating System :: OS Independent
